README.md
setup.py
direct_api/__init__.py
direct_api/client.py
direct_api/entities.py
direct_api/exceptions.py
direct_api/utils.py
yandex_direct_api.egg-info/PKG-INFO
yandex_direct_api.egg-info/SOURCES.txt
yandex_direct_api.egg-info/dependency_links.txt
yandex_direct_api.egg-info/requires.txt
yandex_direct_api.egg-info/top_level.txt