Metadata-Version: 2.1
Name: yandex-direct-api
Version: 0.0.1
Summary: Api wrapper for YandexDirect API v5
Home-page: https://github.com/bzdvdn/yandex-direct-api-wrapper
Author: bzdvdn
Author-email: bzdv.dn@gmail.com
License: MIT
Platform: UNKNOWN
Requires-Python: >=3.6
